{
  "iterations": 100000,
  "comment": "Regional Qualifiers Completed",
  "team_outcomes": {
    "PSG.LGD": {
      "1st": 30224,
      "2nd": 16543,
      "3rd": 10232,
      "4th": 8231,
      "5-6th": 12027,
      "7-8th": 7865,
      "9-12th": 10265,
      "13-16th": 3557,
      "17-18th": 772,
      "19-20th": 284,
      "elim_wc": 0,
      "points_qual": 100000,
      "reg_qual": 0,
      "wc_qual": 0,
      "gr_b_wb": 33352,
      "gr_b_lb": 16735,
      "gr_b_elim": 0,
      "gr_a_wb": 33185,
      "gr_a_lb": 16728,
      "gr_a_elim": 0
    },
    "OG": {
      "1st": 13891,
      "2nd": 12371,
      "3rd": 10295,
      "4th": 9336,
      "5-6th": 14767,
      "7-8th": 11161,
      "9-12th": 16333,
      "13-16th": 8511,
      "17-18th": 2329,
      "19-20th": 1006,
      "elim_wc": 0,
      "points_qual": 100000,
      "reg_qual": 0,
      "wc_qual": 0,
      "gr_b_wb": 33237,
      "gr_b_lb": 16745,
      "gr_b_elim": 0,
      "gr_a_wb": 33473,
      "gr_a_lb": 16545,
      "gr_a_elim": 0
    },
    "beastcoast": {
      "1st": 450,
      "2nd": 1138,
      "3rd": 1854,
      "4th": 2360,
      "5-6th": 6319,
      "7-8th": 8465,
      "9-12th": 21449,
      "13-16th": 28496,
      "17-18th": 15952,
      "19-20th": 13517,
      "elim_wc": 0,
      "points_qual": 100000,
      "reg_qual": 0,
      "wc_qual": 0,
      "gr_a_wb": 33494,
      "gr_a_lb": 16740,
      "gr_a_elim": 0,
      "gr_b_wb": 33299,
      "gr_b_lb": 16467,
      "gr_b_elim": 0
    },
    "Team Spirit": {
      "1st": 9855,
      "2nd": 10233,
      "3rd": 9533,
      "4th": 8815,
      "5-6th": 14878,
      "7-8th": 11758,
      "9-12th": 19032,
      "13-16th": 10949,
      "17-18th": 3277,
      "19-20th": 1670,
      "elim_wc": 0,
      "points_qual": 100000,
      "reg_qual": 0,
      "wc_qual": 0,
      "gr_b_wb": 33301,
      "gr_b_lb": 16662,
      "gr_b_elim": 0,
      "gr_a_wb": 33264,
      "gr_a_lb": 16773,
      "gr_a_elim": 0
    },
    "Team Aster": {
      "1st": 12607,
      "2nd": 11866,
      "3rd": 9964,
      "4th": 8964,
      "5-6th": 14735,
      "7-8th": 11660,
      "9-12th": 17279,
      "13-16th": 9268,
      "17-18th": 2502,
      "19-20th": 1155,
      "elim_wc": 0,
      "points_qual": 100000,
      "reg_qual": 0,
      "wc_qual": 0,
      "gr_a_wb": 33437,
      "gr_a_lb": 16608,
      "gr_a_elim": 0,
      "gr_b_wb": 33428,
      "gr_b_lb": 16527,
      "gr_b_elim": 0
    },
    "Thunder Awaken": {
      "1st": 841,
      "2nd": 1768,
      "3rd": 2658,
      "4th": 3190,
      "5-6th": 8025,
      "7-8th": 9620,
      "9-12th": 22748,
      "13-16th": 27090,
      "17-18th": 13335,
      "19-20th": 10725,
      "elim_wc": 0,
      "points_qual": 100000,
      "reg_qual": 0,
      "wc_qual": 0,
      "gr_a_wb": 33258,
      "gr_a_lb": 16711,
      "gr_a_elim": 0,
      "gr_b_wb": 33351,
      "gr_b_lb": 16680,
      "gr_b_elim": 0
    },
    "BOOM Esports": {
      "1st": 2347,
      "2nd": 3882,
      "3rd": 4815,
      "4th": 5260,
      "5-6th": 11405,
      "7-8th": 12114,
      "9-12th": 23978,
      "13-16th": 21807,
      "17-18th": 8633,
      "19-20th": 5759,
      "elim_wc": 0,
      "points_qual": 100000,
      "reg_qual": 0,
      "wc_qual": 0,
      "gr_a_wb": 33415,
      "gr_a_lb": 16608,
      "gr_a_elim": 0,
      "gr_b_wb": 33269,
      "gr_b_lb": 16708,
      "gr_b_elim": 0
    },
    "TSM FTX": {
      "1st": 1620,
      "2nd": 2869,
      "3rd": 3792,
      "4th": 4301,
      "5-6th": 10359,
      "7-8th": 11500,
      "9-12th": 23989,
      "13-16th": 23912,
      "17-18th": 10324,
      "19-20th": 7334,
      "elim_wc": 0,
      "points_qual": 100000,
      "reg_qual": 0,
      "wc_qual": 0,
      "gr_a_wb": 33175,
      "gr_a_lb": 16468,
      "gr_a_elim": 0,
      "gr_b_wb": 33461,
      "gr_b_lb": 16896,
      "gr_b_elim": 0
    },
    "Tundra Esports": {
      "1st": 2676,
      "2nd": 4156,
      "3rd": 5172,
      "4th": 5610,
      "5-6th": 11849,
      "7-8th": 12257,
      "9-12th": 23907,
      "13-16th": 20766,
      "17-18th": 8350,
      "19-20th": 5257,
      "elim_wc": 0,
      "points_qual": 100000,
      "reg_qual": 0,
      "wc_qual": 0,
      "gr_b_wb": 33440,
      "gr_b_lb": 16458,
      "gr_b_elim": 0,
      "gr_a_wb": 33293,
      "gr_a_lb": 16809,
      "gr_a_elim": 0
    },
    "Gaimin Gladiators": {
      "1st": 373,
      "2nd": 955,
      "3rd": 1618,
      "4th": 1947,
      "5-6th": 5634,
      "7-8th": 7690,
      "9-12th": 20445,
      "13-16th": 28761,
      "17-18th": 16947,
      "19-20th": 15630,
      "elim_wc": 0,
      "points_qual": 100000,
      "reg_qual": 0,
      "wc_qual": 0,
      "gr_b_wb": 33411,
      "gr_b_lb": 16716,
      "gr_b_elim": 0,
      "gr_a_wb": 33223,
      "gr_a_lb": 16650,
      "gr_a_elim": 0
    },
    "Evil Geniuses": {
      "1st": 1224,
      "2nd": 2245,
      "3rd": 3336,
      "4th": 3843,
      "5-6th": 9221,
      "7-8th": 10746,
      "9-12th": 23774,
      "13-16th": 25521,
      "17-18th": 11617,
      "19-20th": 8473,
      "elim_wc": 0,
      "points_qual": 100000,
      "reg_qual": 0,
      "wc_qual": 0,
      "gr_a_wb": 33278,
      "gr_a_lb": 16590,
      "gr_a_elim": 0,
      "gr_b_wb": 33378,
      "gr_b_lb": 16754,
      "gr_b_elim": 0
    },
    "Fnatic": {
      "1st": 1309,
      "2nd": 2612,
      "3rd": 3549,
      "4th": 4010,
      "5-6th": 9552,
      "7-8th": 11097,
      "9-12th": 23865,
      "13-16th": 24753,
      "17-18th": 11073,
      "19-20th": 8180,
      "elim_wc": 0,
      "points_qual": 100000,
      "reg_qual": 0,
      "wc_qual": 0,
      "gr_b_wb": 33073,
      "gr_b_lb": 16652,
      "gr_b_elim": 0,
      "gr_a_wb": 33505,
      "gr_a_lb": 16770,
      "gr_a_elim": 0
    },
    "BetBoom Team": {
      "1st": 2175,
      "2nd": 3611,
      "3rd": 4682,
      "4th": 4991,
      "5-6th": 11050,
      "7-8th": 12080,
      "9-12th": 23968,
      "13-16th": 21730,
      "17-18th": 9324,
      "19-20th": 6389,
      "elim_wc": 0,
      "points_qual": 0,
      "reg_qual": 100000,
      "wc_qual": 0,
      "gr_b_wb": 0,
      "gr_b_lb": 33280,
      "gr_b_elim": 16778,
      "gr_a_wb": 0,
      "gr_a_lb": 33284,
      "gr_a_elim": 16658
    },
    "Entity": {
      "1st": 7934,
      "2nd": 8863,
      "3rd": 8673,
      "4th": 8329,
      "5-6th": 14717,
      "7-8th": 12557,
      "9-12th": 20145,
      "13-16th": 12698,
      "17-18th": 4012,
      "19-20th": 2072,
      "elim_wc": 0,
      "points_qual": 0,
      "reg_qual": 100000,
      "wc_qual": 0,
      "gr_a_wb": 0,
      "gr_a_lb": 33368,
      "gr_a_elim": 16691,
      "gr_b_wb": 0,
      "gr_b_lb": 33371,
      "gr_b_elim": 16570
    },
    "Hokori": {
      "1st": 3,
      "2nd": 18,
      "3rd": 61,
      "4th": 88,
      "5-6th": 473,
      "7-8th": 1175,
      "9-12th": 5424,
      "13-16th": 17401,
      "17-18th": 20636,
      "19-20th": 54721,
      "elim_wc": 0,
      "points_qual": 0,
      "reg_qual": 100000,
      "wc_qual": 0,
      "gr_b_wb": 0,
      "gr_b_lb": 33419,
      "gr_b_elim": 16772,
      "gr_a_wb": 0,
      "gr_a_lb": 33472,
      "gr_a_elim": 16337
    },
    "Soniqs": {
      "1st": 746,
      "2nd": 1632,
      "3rd": 2470,
      "4th": 2843,
      "5-6th": 7548,
      "7-8th": 9449,
      "9-12th": 22515,
      "13-16th": 26849,
      "17-18th": 14021,
      "19-20th": 11927,
      "elim_wc": 0,
      "points_qual": 0,
      "reg_qual": 100000,
      "wc_qual": 0,
      "gr_a_wb": 0,
      "gr_a_lb": 33331,
      "gr_a_elim": 16689,
      "gr_b_wb": 0,
      "gr_b_lb": 33358,
      "gr_b_elim": 16622
    },
    "Talon": {
      "1st": 211,
      "2nd": 605,
      "3rd": 1153,
      "4th": 1507,
      "5-6th": 4630,
      "7-8th": 6586,
      "9-12th": 18274,
      "13-16th": 28745,
      "17-18th": 18373,
      "19-20th": 19916,
      "elim_wc": 0,
      "points_qual": 0,
      "reg_qual": 100000,
      "wc_qual": 0,
      "gr_a_wb": 0,
      "gr_a_lb": 33355,
      "gr_a_elim": 16886,
      "gr_b_wb": 0,
      "gr_b_lb": 33187,
      "gr_b_elim": 16572
    },
    "Royal Never Give Up": {
      "1st": 8095,
      "2nd": 9075,
      "3rd": 8807,
      "4th": 8493,
      "5-6th": 14778,
      "7-8th": 12353,
      "9-12th": 20012,
      "13-16th": 12442,
      "17-18th": 3917,
      "19-20th": 2028,
      "elim_wc": 0,
      "points_qual": 0,
      "reg_qual": 100000,
      "wc_qual": 0,
      "gr_b_wb": 0,
      "gr_b_lb": 33385,
      "gr_b_elim": 16686,
      "gr_a_wb": 0,
      "gr_a_lb": 33190,
      "gr_a_elim": 16739
    },
    "Natus Vincere": {
      "1st": 25,
      "2nd": 51,
      "3rd": 117,
      "4th": 161,
      "5-6th": 476,
      "7-8th": 737,
      "9-12th": 2137,
      "13-16th": 3658,
      "17-18th": 2456,
      "19-20th": 2628,
      "elim_wc": 78477,
      "points_qual": 0,
      "reg_qual": 0,
      "wc_qual": 12446,
      "gr_b_wb": 0,
      "gr_b_lb": 0,
      "gr_b_elim": 6177,
      "gr_a_wb": 0,
      "gr_a_lb": 0,
      "gr_a_elim": 6269
    },
    "Team Secret": {
      "1st": 811,
      "2nd": 1234,
      "3rd": 1717,
      "4th": 1825,
      "5-6th": 3852,
      "7-8th": 4115,
      "9-12th": 8360,
      "13-16th": 7496,
      "17-18th": 3128,
      "19-20th": 2175,
      "elim_wc": 53451,
      "points_qual": 0,
      "reg_qual": 0,
      "wc_qual": 34713,
      "gr_a_wb": 0,
      "gr_a_lb": 0,
      "gr_a_elim": 17326,
      "gr_b_wb": 0,
      "gr_b_lb": 0,
      "gr_b_elim": 17387
    },
    "Virtus.pro": {
      "1st": 1216,
      "2nd": 1852,
      "3rd": 2151,
      "4th": 2299,
      "5-6th": 4827,
      "7-8th": 4743,
      "9-12th": 9187,
      "13-16th": 7757,
      "17-18th": 3024,
      "19-20th": 1908,
      "elim_wc": 49268,
      "points_qual": 0,
      "reg_qual": 0,
      "wc_qual": 38964,
      "gr_b_wb": 0,
      "gr_b_lb": 0,
      "gr_b_elim": 19503,
      "gr_a_wb": 0,
      "gr_a_lb": 0,
      "gr_a_elim": 19461
    },
    "T1": {
      "1st": 3,
      "2nd": 18,
      "3rd": 66,
      "4th": 79,
      "5-6th": 247,
      "7-8th": 398,
      "9-12th": 1506,
      "13-16th": 2654,
      "17-18th": 1977,
      "19-20th": 2438,
      "elim_wc": 82448,
      "points_qual": 0,
      "reg_qual": 0,
      "wc_qual": 9386,
      "gr_b_wb": 0,
      "gr_b_lb": 0,
      "gr_b_elim": 4771,
      "gr_a_wb": 0,
      "gr_a_lb": 0,
      "gr_a_elim": 4615
    },
    "Polaris Esports": {
      "1st": 1,
      "2nd": 7,
      "3rd": 13,
      "4th": 20,
      "5-6th": 79,
      "7-8th": 167,
      "9-12th": 606,
      "13-16th": 1451,
      "17-18th": 1298,
      "19-20th": 1988,
      "elim_wc": 88187,
      "points_qual": 0,
      "reg_qual": 0,
      "wc_qual": 5630,
      "gr_a_wb": 0,
      "gr_a_lb": 0,
      "gr_a_elim": 2820,
      "gr_b_wb": 0,
      "gr_b_lb": 0,
      "gr_b_elim": 2810
    },
    "Wildcard Gaming": {
      "1st": 0,
      "2nd": 2,
      "3rd": 0,
      "4th": 3,
      "5-6th": 15,
      "7-8th": 30,
      "9-12th": 154,
      "13-16th": 544,
      "17-18th": 629,
      "19-20th": 1336,
      "elim_wc": 93271,
      "points_qual": 0,
      "reg_qual": 0,
      "wc_qual": 2713,
      "gr_a_wb": 0,
      "gr_a_lb": 0,
      "gr_a_elim": 1350,
      "gr_b_wb": 0,
      "gr_b_lb": 0,
      "gr_b_elim": 1363
    },
    "Vici Gaming": {
      "1st": 133,
      "2nd": 300,
      "3rd": 473,
      "4th": 572,
      "5-6th": 1648,
      "7-8th": 1957,
      "9-12th": 4786,
      "13-16th": 5910,
      "17-18th": 3129,
      "19-20th": 2634,
      "elim_wc": 67106,
      "points_qual": 0,
      "reg_qual": 0,
      "wc_qual": 21542,
      "gr_b_wb": 0,
      "gr_b_lb": 0,
      "gr_b_elim": 10692,
      "gr_a_wb": 0,
      "gr_a_lb": 0,
      "gr_a_elim": 10850
    },
    "Team Liquid": {
      "1st": 848,
      "2nd": 1383,
      "3rd": 1831,
      "4th": 1778,
      "5-6th": 4055,
      "7-8th": 4344,
      "9-12th": 8303,
      "13-16th": 7574,
      "17-18th": 3097,
      "19-20th": 1999,
      "elim_wc": 52943,
      "points_qual": 0,
      "reg_qual": 0,
      "wc_qual": 35212,
      "gr_a_wb": 0,
      "gr_a_lb": 0,
      "gr_a_elim": 17735,
      "gr_b_wb": 0,
      "gr_b_lb": 0,
      "gr_b_elim": 17477
    },
    "nouns": {
      "1st": 4,
      "2nd": 5,
      "3rd": 25,
      "4th": 39,
      "5-6th": 152,
      "7-8th": 282,
      "9-12th": 899,
      "13-16th": 1941,
      "17-18th": 1642,
      "19-20th": 2262,
      "elim_wc": 85804,
      "points_qual": 0,
      "reg_qual": 0,
      "wc_qual": 7251,
      "gr_b_wb": 0,
      "gr_b_lb": 0,
      "gr_b_elim": 3662,
      "gr_a_wb": 0,
      "gr_a_lb": 0,
      "gr_a_elim": 3589
    },
    "Tempest": {
      "1st": 0,
      "2nd": 0,
      "3rd": 0,
      "4th": 0,
      "5-6th": 5,
      "7-8th": 9,
      "9-12th": 85,
      "13-16th": 364,
      "17-18th": 465,
      "19-20th": 1028,
      "elim_wc": 94677,
      "points_qual": 0,
      "reg_qual": 0,
      "wc_qual": 1956,
      "gr_b_wb": 0,
      "gr_b_lb": 0,
      "gr_b_elim": 999,
      "gr_a_wb": 0,
      "gr_a_lb": 0,
      "gr_a_elim": 957
    },
    "Infamous Gaming": {
      "1st": 0,
      "2nd": 0,
      "3rd": 0,
      "4th": 2,
      "5-6th": 8,
      "7-8th": 22,
      "9-12th": 119,
      "13-16th": 358,
      "17-18th": 490,
      "19-20th": 1168,
      "elim_wc": 94294,
      "points_qual": 0,
      "reg_qual": 0,
      "wc_qual": 2167,
      "gr_b_wb": 0,
      "gr_b_lb": 0,
      "gr_b_elim": 1092,
      "gr_a_wb": 0,
      "gr_a_lb": 0,
      "gr_a_elim": 1075
    },
    "Xtreme Gaming": {
      "1st": 378,
      "2nd": 706,
      "3rd": 943,
      "4th": 1104,
      "5-6th": 2669,
      "7-8th": 3063,
      "9-12th": 6456,
      "13-16th": 7037,
      "17-18th": 3271,
      "19-20th": 2393,
      "elim_wc": 60074,
      "points_qual": 0,
      "reg_qual": 0,
      "wc_qual": 28020,
      "gr_b_wb": 0,
      "gr_b_lb": 0,
      "gr_b_elim": 14067,
      "gr_a_wb": 0,
      "gr_a_lb": 0,
      "gr_a_elim": 13953
    }
  },
  "updated": "23 September 2022 15:55:08",
  "min_threshold": 1020,
  "max_threshold": 1020,
  "avg_threshold": 1020.0000000025944
}